LICENSE
README.md
setup.py
authoriz/__init__.py
authoriz/apps.py
authoriz/cache.py
authoriz/config.py
authoriz/dataclasses.py
authoriz/mixins.py
authoriz/service.py
authoriz.egg-info/PKG-INFO
authoriz.egg-info/SOURCES.txt
authoriz.egg-info/dependency_links.txt
authoriz.egg-info/requires.txt
authoriz.egg-info/top_level.txt
authoriz/migrations/__init__.py
authoriz/namespaces/__init__.py
authoriz/namespaces/base.py
authoriz/parsing/__init__.py
authoriz/parsing/base.py
authoriz/parsing/parsers.py
authoriz/parsing/service.py
authoriz/permissions/__init__.py
authoriz/permissions/base.py
authoriz/tests/__init__.py
authoriz/tests/dataclasses/__init__.py
authoriz/tests/dataclasses/tests.py
authoriz/tests/parsing/__init__.py
authoriz/tests/parsing/tests.py
authoriz/tests/parsing/utils.py
authoriz/tests/permissions/__init__.py
authoriz/tests/permissions/tests.py
authoriz/utils/__init__.py
authoriz/utils/config.py
authoriz/utils/decorators.py
authoriz/utils/parsing.py
authoriz/utils/permissions.py
authoriz/utils/resolving.py
authoriz/utils/roles.py